<?xml version="1.0" encoding="utf-8"?>
<!DOCTYPE hibernate-mapping PUBLIC "-//Hibernate/Hibernate Mapping DTD 3.0//EN"
"http://hibernate.sourceforge.net/hibernate-mapping-3.0.dtd">
<!-- 
    Mapping file autogenerated by MyEclipse Persistence Tools
-->
<hibernate-mapping>
    <class name="com.ailk.sets.platform.domain.ConfigSysParameters" table="config_sys_parameters">
        <id name="paramId" type="java.lang.Integer">
            <column name="param_id" />
            <generator class="assigned" />
        </id>
        <property name="paramName" type="java.lang.String">
            <column name="param_name" length="64" />
        </property>
        <property name="paramEname" type="java.lang.String">
            <column name="param_ename" length="128" />
        </property>
        <property name="paramDesc" type="java.lang.String">
            <column name="param_desc" />
        </property>
        <property name="paramValue" type="java.lang.String">
            <column name="param_value" length="1000" />
        </property>
    </class>
</hibernate-mapping>
